__init__.py
superphot_plus/__init__.py
superphot_plus/_version.py
superphot_plus/config.py
superphot_plus/constants.py
superphot_plus/supernova_class.py
superphot_plus/trainer.py
superphot_plus/trainer_base.py
superphot_plus/tuner.py
superphot_plus/utils.py
superphot_plus/data_generation/__init__.py
superphot_plus/data_generation/alerce.py
superphot_plus/data_generation/make_fake_spp_data.py
superphot_plus/data_generation/phot.py
superphot_plus/data_generation/snana.py
superphot_plus/data_generation/spec.py
superphot_plus/external_classifiers/parsnip.py
superphot_plus/external_classifiers/superphot.py
superphot_plus/external_classifiers/superraenn.py
superphot_plus/model/__init__.py
superphot_plus/model/classifier.py
superphot_plus/model/lightgbm.py
superphot_plus/model/metrics.py
superphot_plus/model/mlp.py
superphot_plus/plotting/.pymon
superphot_plus/plotting/IN_PROGRESS.py
superphot_plus/plotting/__init__.py
superphot_plus/plotting/classifier_results.py
superphot_plus/plotting/confusion_matrices.py
superphot_plus/plotting/format_params.py
superphot_plus/plotting/lightcurves.py
superphot_plus/plotting/sampling_results.py
superphot_plus/plotting/utils.py
superphot_plus/priors/__init__.py
superphot_plus/priors/generate_prior.py
superphot_plus/priors/priors_ZTF_g.csv
superphot_plus/priors/priors_ZTF_r.csv
superphot_plus/priors/superphot_prior.py
superphot_plus/priors/ztf-Copy1.yaml
superphot_plus/samplers/__init__.py
superphot_plus/samplers/dynesty_sampler.py
superphot_plus/samplers/iminuit_sampler.py
superphot_plus/samplers/licu_sampler.py
superphot_plus/samplers/numpyro_sampler.py
superphot_plus/samplers/superphot_sampler.py
superphot_plus-0.1.0.dist-info/licenses/LICENSE
superphot_plus-0.1.0.dist-info/METADATA
superphot_plus-0.1.0.dist-info/WHEEL
superphot_plus-0.1.0.dist-info/top_level.txt
superphot_plus-0.1.0.dist-info/RECORD
