Metadata-Version: 2.4
Name: superphot-plus
Version: 0.1.0
Author-email: Kaylee de Soto <kaylee.de_soto@cfa.harvard.edu>
License: MIT License
Classifier: Development Status :: 4 - Beta
Classifier: License :: OSI Approved :: MIT License
Classifier: Intended Audience :: Developers
Classifier: Intended Audience :: Science/Research
Classifier: Operating System :: OS Independent
Classifier: Programming Language :: Python
License-File: LICENSE
Requires-Dist: astropy
Requires-Dist: joblib>=1.4.0
Requires-Dist: lightgbm>=4.3.0
Requires-Dist: numpy<1.26.3
Requires-Dist: pandas>=2.0.0
Requires-Dist: scikit-learn>=1.3.2
Requires-Dist: torch>=2.0.0
Requires-Dist: tensorboard>=2.14.0
Requires-Dist: tensorflow_probability>=0.21.0
Provides-Extra: dev
Requires-Dist: ipykernel; extra == "dev"
Requires-Dist: ipython; extra == "dev"
Requires-Dist: nbconvert; extra == "dev"
Requires-Dist: nbsphinx; extra == "dev"
Requires-Dist: nbval; extra == "dev"
Requires-Dist: pytest; extra == "dev"
Requires-Dist: pytest-cov; extra == "dev"
Requires-Dist: pre-commit; extra == "dev"
Requires-Dist: sphinx; extra == "dev"
Requires-Dist: sphinx-rtd-theme; extra == "dev"
Requires-Dist: sphinx-autoapi; extra == "dev"
Requires-Dist: pylint; extra == "dev"
Provides-Extra: sampling
Requires-Dist: dynesty>=2.1.3; extra == "sampling"
Requires-Dist: numpyro>=0.14.0; extra == "sampling"
Requires-Dist: imbalanced-learn>=0.12.2; extra == "sampling"
Requires-Dist: iminuit>=2.25.2; extra == "sampling"
Requires-Dist: light-curve>=0.9; extra == "sampling"
Provides-Extra: plotting
Requires-Dist: arviz; extra == "plotting"
Requires-Dist: colorcet>=3.1.0; extra == "plotting"
Requires-Dist: corner>=2.2.2; extra == "plotting"
Requires-Dist: matplotlib>=3.8.4; extra == "plotting"
Requires-Dist: pacmap>=0.7.2; extra == "plotting"
Requires-Dist: scipy==1.12.0; extra == "plotting"
Provides-Extra: tuning
Requires-Dist: ray[tune]>=2.11.0; extra == "tuning"
Requires-Dist: optuna; extra == "tuning"
Provides-Extra: benchmarking
Requires-Dist: asv>=0.5.1; extra == "benchmarking"
Requires-Dist: memory_profiler>=0.61.0; extra == "benchmarking"
Dynamic: license-file
